rba_cdk/__init__.py
rba_cdk/rba_codepipeline_actions/__init__.py
rba_cdk/rba_codepipeline_actions/codebuild_actions.py
rba_cdk/rba_ecr/__init__.py
rba_cdk/rba_ecr/ecr.py
rba_cdk/rba_pipelines/__init__.py
rba_cdk/rba_pipelines/buildspec_pipeline.py
rba_cdk/rba_pipelines/default_pipeline.py
rba_cdk/rba_pipelines/docker_pipeline.py
rba_cdk/rba_utils/__init__.py
rba_cdk/rba_utils/utils.py
rba_cdk-0.0.100.dist-info/LICENSE.txt
rba_cdk-0.0.100.dist-info/METADATA
rba_cdk-0.0.100.dist-info/WHEEL
rba_cdk-0.0.100.dist-info/top_level.txt
rba_cdk-0.0.100.dist-info/RECORD
