Metadata-Version: 2.1
Name: rba-cdk
Version: 0.0.100
Summary: custom cdk package
Home-page: UNKNOWN
Author: Harry Yang
Author-email: hyang@ritchiebros.com
License: UNKNOWN
Platform: UNKNOWN
Classifier: Intended Audience :: Developers
Classifier: License :: OSI Approved :: Apache Software License
Classifier: Programming Language :: Python :: 3.6
Classifier: Programming Language :: Python :: 3.7
Classifier: Programming Language :: Python :: 3.8
Classifier: Topic :: Software Development :: Code Generators
Classifier: Topic :: Utilities
Classifier: Typing :: Typed
Requires-Python: >=3.6
Requires-Dist: pygit2
Requires-Dist: aws-cdk.core (==1.106.0)
Requires-Dist: aws-cdk.aws-ecr (==1.106.0)
Requires-Dist: aws-cdk.aws-iam (==1.106.0)
Requires-Dist: aws-cdk.aws-codepipeline (==1.106.0)
Requires-Dist: aws-cdk.aws-codepipeline-actions (==1.106.0)
Requires-Dist: aws-cdk.aws-codebuild (==1.106.0)
Requires-Dist: aws-cdk.aws-codecommit (==1.106.0)
Requires-Dist: aws-cdk.pipelines (==1.106.0)
